dataclasses_config/__init__.py
dataclasses_config/_helpers.py
dataclasses_config/backports.py
dataclasses_config/config.py
dataclasses_config/decorations.py
dataclasses_config/errors.py
dataclasses_config/settings.py
dataclasses_config/util.py
dataclasses_config/classes/__init__.py
dataclasses_config/classes/duration.py
dataclasses_config/classes/dynamic_class.py
dataclasses_config/classes/path.py
dataclasses_config-0.4.9.dist-info/LICENSE
dataclasses_config-0.4.9.dist-info/METADATA
dataclasses_config-0.4.9.dist-info/WHEEL
dataclasses_config-0.4.9.dist-info/top_level.txt
dataclasses_config-0.4.9.dist-info/RECORD
